[
    {
        "id": "pallet",
        "town": "Pallet Town",
        "coordinates": {
            "lat": "35.25",
            "lng": "139.65"
        },
        "date": "2024-04-05",
        "images": {
            "photo_1": "/images/towns/pallet/pallet_1.jpeg",
            "photo_2": "/images/towns/pallet/pallet_2.jpeg",
            "photo_3": "/images/towns/pallet/pallet_3.jpeg",
            "descriptions": {
                "desc_1": "Arriving at Pallet Town",
                "desc_2": "Red's House",
                "desc_3": "Inside Prof. Oak's Lab"
            }
        },
        "encounters": {
            "poke_1": "pidgey",
            "poke_2": "rattata",
            "poke_3": "pikachu"
        },
        "summary": "Welcome to Pallet Town, a charming little gem nestled in the Kanto region that feels straight out of a Pokémon adventure!As I strolled through the quaint streets, the nostalgic vibe of this iconic locale washed over me.\nI kicked off my journey at Professor Oak's lab, where I could almost hear the rustling of Poké Balls and the excited chatter of trainers. I took a leisurely walk to the nearby Ash’s house, imagining the countless battles and adventures that originated from this very spot.\nThe picturesque scenery, with lush green fields and a serene lake, invited me to unwind and observe the wild Pokémon. I even spotted a few Butterfree fluttering by!\nFor lunch, I grabbed a meal at a local diner and reminisced about childhood memories of the original series. As the day ended with a breathtaking sunset, I couldn't help but feel that I had stepped into a real-life Pokémon journey.\nPallet Town isn’t just a destination; it’s an experience that ignites the spark of adventure in anyone who visits!"
    },
    {
        "id": "viridian",
        "town": "Viridian City",
        "coordinates": {
            "lat": "35.48",
            "lng": "139.6"
        },
        "date": "2024-04-14",
        "images": {
            "photo_1": "/images/towns/viridian/viridian_1.jpeg",
            "photo_2": "/images/towns/viridian/viridian_2.jpeg",
            "photo_3": "/images/towns/viridian/viridian_3.jpeg",
            "descriptions": {
                "desc_1": "Arriving at Viridian City",
                "desc_2": "The Viridian Forest",
                "desc_3": "Inside the Viridian Gym"
            }
        },
        "encounters": {
            "poke_1": "caterpie",
            "poke_2": "kakuna",
            "poke_3": "bulbasaur"
        },
        "summary": "Welcome to my adventure in Viridian City, a hidden gem in the heart of Kanto! As I travelled around, the lush greenery and vibrant PokéStops captured my attention.\nI kicked off my visit at the iconic Viridian Pokémon Center, buzzing with trainers swapping stories of their battles. After grabbing some delicious Poffins from a local shop, I headed to the Viridian Forest, where I marveled at the beauty of the towering trees and the sounds of wild Pokémon all around.\nThe highlight was battling my way through the Viridian Gym, facing the formidable Leader, Giovanni, and feeling the rush of strategy and excitement.\nAs the sun set, painting the sky in hues of orange and pink, I savored a delicious meal at a charming café while reflecting on the dynamic spirit of this legendary city.\nI can’t wait to share more about my next adventures in Kanto!"
    },
    {
        "id": "pewter",
        "town": "Pewter City",
        "coordinates": {
            "lat": "35.62",
            "lng": "139.68"
        },
        "date": "2024-05-12",
        "images": {
            "photo_1": "/images/towns/pewter/pewter_1.jpeg",
            "photo_2": "/images/towns/pewter/pewter_2.jpeg",
            "photo_3": "/images/towns/pewter/pewter_3.jpeg",
            "descriptions": {
                "desc_1": "Arriving at Pewter City",
                "desc_2": "Inside the Pokemon Museum",
                "desc_3": "The caves of Mt. Moon"
            }
        },
        "encounters": {
            "poke_1": "geodude",
            "poke_2": "zubat",
            "poke_3": "omanyte"
        },
        "summary": "As I stepped off the train in Pewter City, the crisp air filled with the scent of pine and adventure greeted me. The charming blend of natural beauty and rich Pokémon history was immediately captivating.\nMy first stop was the Pewter Museum of Science, where I marveled at the fascinating exhibits on fossils highlighting the extinct Omanyte, making me feel connected to the past.\nAfter soaking up knowledge, I strolled to the iconic Pewter Gym, a stunning stone structure where I cheered on aspiring trainers against the imposing Brock.\nThe afternoon was delightfully spent exploring the serene Pewter City Park, where I relaxed near the beautiful waterfalls and enjoyed a picnic amid playful Pokémon.\nAs the sun set, I ended my day with a memorable visit to a local Poké Mart, stocking up on rare items before heading back to my cozy inn, filled with excitement for the adventures still to come in Kanto."
    },
    {
        "id": "cerulean",
        "town": "Cerulean City",
        "coordinates": {
            "lat": "35.6",
            "lng": "140.23"
        },
        "date": "2024-06-15",
        "images": {
            "photo_1": "/images/towns/cerulean/cerulean_1.jpeg",
            "photo_2": "/images/towns/cerulean/cerulean_2.jpeg",
            "photo_3": "/images/towns/cerulean/cerulean_3.jpeg",
            "descriptions": {
                "desc_1": "Arriving at Cerulean City",
                "desc_2": "Inside the Cerulean Gym",
                "desc_3": "The Nugget Bridge"
            }
        },
        "encounters": {
            "poke_1": "magikarp",
            "poke_2": "oddish",
            "poke_3": "poliwag"
        },
        "summary": "This was a remarkable trip to Cerulean City in Kanto, where the vibrant blue waters and charming sights left me in awe!\nI began my adventure at the iconic Cerulean Cape, where I soaked in stunning views and even spotted a few playful Water Pokémon. The highlight was undoubtedly my visit to the Cerulean Gym, where I challenged Misty and was thrilled to watch her battle techniques up close.\nAfter a refreshing stroll through the Cerulean Market, where locals showcased their handmade crafts, I treated myself to some delicious sea-themed snacks.\nAs evening fell, the city transformed, with the serene lights reflecting off the water in which I found a shiny Magikarp—a perfect end to my day.\nCerulean City is a gem in Kanto, a must-visit for any Pokémon enthusiast or traveler seeking a slice of tranquility and adventure!"
    },
    {
        "id": "vermilion",
        "town": "Vermilion City",
        "coordinates": {
            "lat": "35.23",
            "lng": "139.88"
        },
        "date": "2024-07-13",
        "images": {
            "photo_1": "/images/towns/vermilion/vermilion_1.jpeg",
            "photo_2": "/images/towns/vermilion/vermilion_2.jpeg",
            "photo_3": "/images/towns/vermilion/vermilion_3.jpeg",
            "descriptions": {
                "desc_1": "Arriving at Vermilion City",
                "desc_2": "Inside the S.S. Anne",
                "desc_3": "Diglett's Cave"
            }
        },
        "encounters": {
            "poke_1": "diglett",
            "poke_2": "meowth",
            "poke_3": "drowzee"
        },
        "summary": "As I embarked on my journey to Vermilion City in the Kanto region, the vibrant streets and the salty sea breeze instantly filled me with excitement.\nMy first stop was the bustling Vermilion Harbor, teeming with fishermen and trainers preparing for their next big catch. I savored a delicious bowl of freshly caught Magikarp sashimi at a local eatery, an unexpected culinary delight.\nAfter exploring the iconic Vermilion Pokémon Center, where I recharged my team, I strolled along the scenic coastline, captivated by the sunset casting golden hues over the harbor.\nA visit to the S.S. Anne was the highlight of my trip; the luxury ship, filled with trainers and intriguing characters, buzzed with energy.\nAs I waved goodbye to this charming city, I couldn't help but feel grateful for the unforgettable memories and the adventures that awaited in the heart of Kanto."
    },
    {
        "id": "lavender",
        "town": "Lavender Town",
        "coordinates": {
            "lat": "35.43",
            "lng": "140.38"
        },
        "date": "2024-07-31",
        "images": {
            "photo_1": "/images/towns/lavender/lavender_1.jpeg",
            "photo_2": "/images/towns/lavender/lavender_2.jpeg",
            "photo_3": "/images/towns/lavender/lavender_3.jpeg",
            "descriptions": {
                "desc_1": "Arriving at Lavender Town",
                "desc_2": "Graveyard next to Pokemon Tower",
                "desc_3": "The city's lavenders"
            }
        },
        "encounters": {
            "poke_1": "gastly",
            "poke_2": "haunter",
            "poke_3": "cubone"
        },
        "summary": "As I stepped into Lavender Town, the air thick with an enchanting mix of nostalgia and mystery, I was immediately wrapped in the soothing scent of lavender wafting through the streets.\nThe sky painted hues of lavender and soft blues created a mesmerizing backdrop as I strolled past the iconic Pokémon Tower, where whispers of ghostly legends intertwined with the vibrant history of this charming town.\nI visited the serene Pokémon graveyard, paying my respects and feeling a profound connection to the trainers who had walked these paths before me.\nThe quaint souvenir shops offered a delightful assortment of lavender-infused treats and unique memorabilia, making it hard to leave without a piece of this magical town.\nAs night fell, the eerie yet beautiful atmosphere of Lavender Town, illuminated by soft lanterns, captivated me, leaving me with unforgettable memories of my tranquil adventure in the heart of Kanto."
    },
    {
        "id": "celadon",
        "town": "Celadon City",
        "coordinates": {
            "lat": "35.35",
            "lng": "139.98"
        },
        "date": "2024-08-02",
        "images": {
            "photo_1": "/images/towns/celadon/celadon_1.jpeg",
            "photo_2": "/images/towns/celadon/celadon_2.jpeg",
            "photo_3": "/images/towns/celadon/celadon_3.jpeg",
            "descriptions": {
                "desc_1": "Arriving at Celadon City ",
                "desc_2": "Celadon Department Store",
                "desc_3": "Celadon Game Corner"
            }
        },
        "encounters": {
            "poke_1": "gloom",
            "poke_2": "weepinbell",
            "poke_3": "eevee"
        },
        "summary": "Exploring Celadon City in Kanto was an enchanting experience filled with vibrant sights and sounds!\nUpon arrival, I was immediately captivated by the lush greenery of the Celadon Department Store and the surrounding gardens, which provided a calming escape from the hustle and bustle of city life. I spent my morning wandering through the iconic shopping district, where I discovered unique Pokémon merchandise and delicious pastries at the café.\nThe highlight of my day was visiting the Celadon Gym, where I cheered on trainers as they faced off against the formidable Grass-type Gym Leader.\nI also strolled through the serene Celadon City Park, soaking in the beauty of the flowers and watching trainers battle their Pokémon in the sunshine.\nCeladon City truly felt like a harmonious blend of nature and urban life, making it an unforgettable stop on my Kanto adventure!"
    },
    {
        "id": "fuchsia",
        "town": "Fuchsia City",
        "coordinates": {
            "lat": "34.92",
            "lng": "139.88"
        },
        "date": "2024-08-23",
        "images": {
            "photo_1": "/images/towns/fuchsia/fuchsia_1.jpeg",
            "photo_2": "/images/towns/fuchsia/fuchsia_2.jpeg",
            "photo_3": "/images/towns/fuchsia/fuchsia_3.jpeg",
            "descriptions": {
                "desc_1": "Arriving at Fuchsia City",
                "desc_2": "The Safari Zone",
                "desc_3": "The Seafoam Islands"
            }
        },
        "encounters": {
            "poke_1": "tauros",
            "poke_2": "chansey",
            "poke_3": "scyther"
        },
        "summary": "What an unforgettable trip to Fuchsia City, the hidden gem of Kanto!\nNestled along the coast, I was immediately enchanted by the vibrant flora that lines the streets, with fuchsia flowers blooming everywhere. I explored the famous Safari Zone, where I caught glimpses of rare Pokémon in their natural habitats—truly a dream come true for any trainer!\nAfter a thrilling day of wild encounters, I relaxed by the beach, savoring some delicious local cuisine featuring fresh seafood.\nThe charm of Fuchsia City extended to the warm hospitality of its residents, who shared tales of their own Pokémon adventures.\nAs the sun set, painting the skies in shades of pink and purple, I felt a deep connection to this enchanting city and its thriving Pokémon culture—a perfect blend of adventure and tranquility. I can't wait to return!"
    },
    {
        "id": "saffron",
        "town": "Saffron City",
        "coordinates": {
            "lat": "35.3",
            "lng": "140.16"
        },
        "date": "2024-09-27",
        "images": {
            "photo_1": "/images/towns/saffron/saffron_1.jpeg",
            "photo_2": "/images/towns/saffron/saffron_2.jpeg",
            "photo_3": "/images/towns/saffron/saffron_3.jpeg",
            "descriptions": {
                "desc_1": "Arriving at Saffron City",
                "desc_2": "Breakfast at the Saffron Cafe",
                "desc_3": "The Fighting Dojo"
            }
        },
        "encounters": {
            "poke_1": "kadabra",
            "poke_2": "hitmonlee",
            "poke_3": "hitmonchan"
        },
        "summary": "Welcome to my adventure in Saffron City, the bustling heart of the Kanto region!\nMy journey began as I stepped off the train at Saffron's sleek station, greeted by the towering Skyscrapers and neon lights that defined this urban Pokémon paradise.\nI indulged in a delightful cup of Saffron's famous tea at the Saffron Cafe before exploring the vibrant streets filled with trainers and their Pokémon. The Pokémon Center buzzed with excitement, and I even took a moment to challenge the impressive Psychic-type Gym, led by the enigmatic Sabrina.\nAfter a day of battles and shopping at the renowned Silph Co. and local boutiques, I watched a breathtaking sunset from the rooftops, reflecting on the lively energy that makes Saffron City unforgettable.\nThis trip was not just about catching Pokémon, but embracing the lively culture and spirit that make Kanto so special!"
    },
    {
        "id": "cinnabar",
        "town": "Cinnabar Island",
        "coordinates": {
            "lat": "34.74",
            "lng": "139.4"
        },
        "date": "2024-10-07",
        "images": {
            "photo_1": "/images/towns/cinnabar/cinnabar_1.jpeg",
            "photo_2": "/images/towns/cinnabar/cinnabar_2.jpeg",
            "photo_3": "/images/towns/cinnabar/cinnabar_3.jpeg",
            "descriptions": {
                "desc_1": "Arriving at Cinnabar Island",
                "desc_2": "The Pokemon Mansion",
                "desc_3": "Inside Cinnabar Lab"
            }
        },
        "encounters": {
            "poke_1": "growlithe",
            "poke_2": "ditto",
            "poke_3": "magmar"
        },
        "summary": "Stepping off the ferry onto Cinnabar Island felt like entering a vibrant postcard; the air was warm and tinged with the salty sea breeze.\nMy adventure began with a leisurely stroll along the coastline, where the shimmering waves perfectly matched the azure sky.\nI explored the iconic Cinnabar Volcano, marveling at its rugged terrain and the unique Pokémon that roamed the area. The highlight of my day was visiting the Cinnabar Island Mansion, a mysterious relic filled with intriguing lore and hidden collectibles.\nAfter capturing stunning photographs and catching a few rare Pokémon, I wrapped up my outing at a cozy café, sipping on a refreshing drink crafted from the island's famous berries.\nAs the sun began to set, casting golden hues over the horizon, I couldn’t help but feel grateful for the day's unforgettable experiences on this enchanting island."
    }
]